evtech/__init__.py
evtech/camera.py
evtech/dataset.py
evtech/geodesy.py
evtech/ray.py
evtech-1.1.0.dist-info/AUTHORS.rst
evtech-1.1.0.dist-info/LICENSE
evtech-1.1.0.dist-info/METADATA
evtech-1.1.0.dist-info/WHEEL
evtech-1.1.0.dist-info/top_level.txt
evtech-1.1.0.dist-info/RECORD
