Metadata-Version: 2.1
Name: evtech
Version: 1.1.0
Summary: Tools for RIT Hack.tiff 2020 Hackathon
Home-page: https://github.com/dnilosek/evtech
Author: David Nilosek
Author-email: david.nilosek@eagleview.com
License: MIT license
Keywords: evtech
Platform: UNKNOWN
Classifier: Development Status :: 2 - Pre-Alpha
Classifier: Intended Audience :: Developers
Classifier: License :: OSI Approved :: MIT License
Classifier: Natural Language :: English
Classifier: Programming Language :: Python :: 3
Classifier: Programming Language :: Python :: 3.6
Classifier: Programming Language :: Python :: 3.7
Classifier: Programming Language :: Python :: 3.8
Requires-Python: >=3.6
